README.md
dailymotion.py
setup.cfg
setup.py
xupload.py
dailymotion.egg-info/PKG-INFO
dailymotion.egg-info/SOURCES.txt
dailymotion.egg-info/dependency_links.txt
dailymotion.egg-info/not-zip-safe
dailymotion.egg-info/requires.txt
dailymotion.egg-info/top_level.txt