Metadata-Version: 1.1
Name: dailymotion
Version: 0.2.5
Summary: Dailymotion API SDK
Home-page: http://github.com/dailymotion/dailymotion-sdk-python
Author: Samir AMZANI
Author-email: samir.amzani@gmail.com
License: Apache License, Version 2.0
Keywords: dailymotion,api,sdk,graph
Platform: UNKNOWN
Classifier: Programming Language :: Python
Classifier: Development Status :: 5 - Production/Stable
Classifier: Intended Audience :: Developers
Classifier: License :: OSI Approved :: Apache Software License
Classifier: Operating System :: MacOS :: MacOS X
Classifier: Operating System :: Microsoft :: Windows
Classifier: Operating System :: POSIX
Classifier: Programming Language :: Python :: 3
